ilo_binding/__init__.py
ilo_binding/trame_builder.py
ilo_binding-1.0.0.dist-info/METADATA
ilo_binding-1.0.0.dist-info/WHEEL
ilo_binding-1.0.0.dist-info/top_level.txt
ilo_binding-1.0.0.dist-info/RECORD
