Metadata-Version: 2.4
Name: ilo_binding
Version: 1.0.0
Summary: Python binding for the ilo protocol
Author: Sigmanificient
Author-email: yohann.boniface@epitech.eu
License: MIT
Platform: unix
Platform: linux
Platform: osx
Classifier: Intended Audience :: Developers
Classifier: Programming Language :: Python :: 3 :: Only
Requires-Python: >=3.8
